MANIFEST.in
README.md
setup.cfg
setup.py
pytest_redmine/__init__.py
pytest_redmine/plugin.py
pytest_redmine.egg-info/PKG-INFO
pytest_redmine.egg-info/SOURCES.txt
pytest_redmine.egg-info/dependency_links.txt
pytest_redmine.egg-info/entry_points.txt
pytest_redmine.egg-info/requires.txt
pytest_redmine.egg-info/top_level.txt